jsmsgr/__init__.py
jsmsgr/api.py
jsmsgr/apps.py
jsmsgr/sanity_check.py
jsmsgr/settings.py
jsmsgr/core/__init__.py
jsmsgr/core/messaging.py
jsmsgr/core/msg_builders.py
jsmsgr/core/msg_processing.py
jsmsgr/support/__init__.py
jsmsgr/support/misc.py
jsmsgr/support/user.py
jsmsgr-0.0.11.dist-info/METADATA
jsmsgr-0.0.11.dist-info/WHEEL
jsmsgr-0.0.11.dist-info/top_level.txt
jsmsgr-0.0.11.dist-info/RECORD
