Metadata-Version: 2.1
Name: jsmsgr
Version: 0.0.11
Summary: Django app to make sending transactional messages to Semaphore a breeze!
Home-page: https://github.com/juntossomosmais/jsmsgr
Author: Juntos Somos Mais
License: UNKNOWN
Platform: UNKNOWN
Classifier: Programming Language :: Python
Classifier: Programming Language :: Python :: 3.7
Classifier: Framework :: Django :: 2.1
Classifier: Environment :: Web Environment
Classifier: Natural Language :: Portuguese (Brazilian)
Classifier: Development Status :: 4 - Beta
Classifier: Framework :: Django
Classifier: Intended Audience :: Developers
Classifier: Operating System :: OS Independent
Requires-Dist: jsm-user-services (>=0.2.0)
Requires-Dist: django (>=1.11)
Requires-Dist: django-stomp (>=0.0.19)
